m2pytorch/__init__.py
m2pytorch/main.py
m2pytorch-1.3.6.dist-info/LICENSE.txt
m2pytorch-1.3.6.dist-info/METADATA
m2pytorch-1.3.6.dist-info/WHEEL
m2pytorch-1.3.6.dist-info/top_level.txt
m2pytorch-1.3.6.dist-info/RECORD
